roam.py
roam-0.3.1.dist-info/LICENSE
roam-0.3.1.dist-info/WHEEL
roam-0.3.1.dist-info/METADATA
roam-0.3.1.dist-info/RECORD
